{"frontMatter":{"slug":"check-prime-number","title":"Check Prime Number","description":"Write a program to check prime number","tags":[],"contributors":["dylan-power","karthiksbh","NeelPatel31","rutterjt","MadhuS-1605","umaxyon"]},"latestUpdateDate":"2022-06-27T14:11:18Z","contentHtml":"<h2>Write a program to check prime number</h2>\n<pre><code>Input  : 7\nOutput : Prime number\n</code></pre>\n<hr>\n","markdown":"\n## Write a program to check prime number\n\n```txt\nInput  : 7\nOutput : Prime number\n```\n\n---\n"}