{"frontMatter":{"slug":"check-leap-year","title":"Check Leap Year","description":"Write a programme to check leap year","tags":[],"contributors":["saikatg347","RuiL1904","rootzer00","Anzo52","MadhuS-1605","IrumiDesu7","umaxyon"]},"latestUpdateDate":"2022-06-27T14:11:18Z","contentHtml":"<h2>Write a programme to check leap year</h2>\n<pre><code>Input  : 2020\nOutput : Leap Year\n</code></pre>\n<pre><code>Input  : 2021\nOutput : Not a Leap Year\n</code></pre>\n<hr>\n","markdown":"\n## Write a programme to check leap year\n\n```txt\nInput  : 2020\nOutput : Leap Year\n```\n\n```txt\nInput  : 2021\nOutput : Not a Leap Year\n```\n\n---\n"}